CHANGES.txt
COPYRIGHT.txt
LICENSE.txt
README.txt
bootstrap.py
buildout.cfg
setup.py
src/megrok/__init__.py
src/megrok.rdb.egg-info/PKG-INFO
src/megrok.rdb.egg-info/SOURCES.txt
src/megrok.rdb.egg-info/dependency_links.txt
src/megrok.rdb.egg-info/entry_points.txt
src/megrok.rdb.egg-info/namespace_packages.txt
src/megrok.rdb.egg-info/not-zip-safe
src/megrok.rdb.egg-info/requires.txt
src/megrok.rdb.egg-info/top_level.txt
src/megrok/rdb/README.txt
src/megrok/rdb/__init__.py
src/megrok/rdb/components.py
src/megrok/rdb/configure.zcml
src/megrok/rdb/directive.py
src/megrok/rdb/interfaces.py
src/megrok/rdb/meta.py
src/megrok/rdb/meta.zcml
src/megrok/rdb/prop.py
src/megrok/rdb/schema.py
src/megrok/rdb/schema.txt
src/megrok/rdb/setup.py
src/megrok/rdb/sorted_inheritance.py
src/megrok/rdb/testing.py
src/megrok/rdb/tests/__init__.py
src/megrok/rdb/tests/creation.py
src/megrok/rdb/tests/explicittable.py
src/megrok/rdb/tests/initialization.py
src/megrok/rdb/tests/location.py
src/megrok/rdb/tests/polymorphic.py
src/megrok/rdb/tests/reflection.py
src/megrok/rdb/tests/tableargs.py
src/megrok/rdb/tests/test_rdb.py