Metadata-Version: 1.0
Name: megrok.rdb
Version: 0.12
Summary: SQLAlchemy based RDB support for Grok.
Home-page: UNKNOWN
Author: Grok Team
Author-email: grok-dev@zope.org
License: ZPL
Keywords: rdb relational sqlalchemy grok database
Platform: UNKNOWN
Classifier: Development Status :: 4 - Beta
Classifier: Environment :: Web Environment
Classifier: Framework :: Zope3
Classifier: Intended Audience :: Developers
Classifier: License :: OSI Approved :: Zope Public License
Classifier: Operating System :: OS Independent
Classifier: Programming Language :: Python
Classifier: Topic :: Internet :: WWW/HTTP
Classifier: Topic :: Software Development :: Libraries
Classifier: Topic :: Database
